PLD_subsampling/PLD_subsampling_impl.py
PLD_subsampling/__init__.py
PLD_subsampling/main.py
PLD_subsampling/testing/__init__.py
PLD_subsampling/testing/analytic_Gaussian.py
PLD_subsampling/testing/plot_utils.py
PLD_subsampling/testing/test_utils.py
PLD_subsampling/wrappers/__init__.py
PLD_subsampling/wrappers/dp_accounting_wrappers.py
pld_subsampling-0.1.6.dist-info/METADATA
pld_subsampling-0.1.6.dist-info/WHEEL
pld_subsampling-0.1.6.dist-info/top_level.txt
pld_subsampling-0.1.6.dist-info/RECORD
