Metadata-Version: 2.4
Name: PLD-subsampling
Version: 0.1.6
Summary: PLD PMF/PLD transformations: subsampling amplification and infinity-mass scaling utilities
Author: Moshe Shenfeld
License: Apache-2.0
Project-URL: Homepage, https://github.com/moshenfeld/PLD_subsampling
Project-URL: Repository, https://github.com/moshenfeld/PLD_subsampling.git
Keywords: differential-privacy,privacy-loss-distribution,subsampling,dp,pld
Classifier: Development Status :: 3 - Alpha
Classifier: Intended Audience :: Science/Research
Classifier: License :: OSI Approved :: Apache Software License
Classifier: Programming Language :: Python :: 3
Classifier: Programming Language :: Python :: 3.9
Classifier: Programming Language :: Python :: 3.10
Classifier: Programming Language :: Python :: 3.11
Classifier: Programming Language :: Python :: 3.12
Classifier: Topic :: Scientific/Engineering
Requires-Python: >=3.9
Requires-Dist: numpy>=1.24
Requires-Dist: scipy>=1.10
Requires-Dist: matplotlib>=3.7
Requires-Dist: dp-accounting>=0.5.0
